smartpost/__init__.py
smartpost/api.py
smartpost/errors.py
smartpost/models.py
smartpost-0.1.0.dist-info/LICENSE
smartpost-0.1.0.dist-info/WHEEL
smartpost-0.1.0.dist-info/METADATA
smartpost-0.1.0.dist-info/RECORD
